examples/__init__.py
examples/fast_api.py
payze/__init__.py
payze/client.py
payze/param/__init__.py
payze/param/ops/__init__.py
payze/param/ops/client.py
payze/param/request/__init__.py
payze/param/request/base.py
payze/param/request/just_pay.py
payze/param/response/__init__.py
payze/param/response/base.py
payze/param/response/just_pay.py
payze/param/webhook/__init__.py
payze/param/webhook/base.py
payze/param/webhook/just_pay.py
payze_pkg-2.6.dist-info/METADATA
payze_pkg-2.6.dist-info/WHEEL
payze_pkg-2.6.dist-info/top_level.txt
payze_pkg-2.6.dist-info/RECORD
