Metadata-Version: 2.1
Name: payze-pkg
Version: 2.6
Home-page: https://github.com/PayTechUz/payze-pkg
Author: paytechuz
Author-email: paytechuz@gmail.com
License: MIT
Keywords: payze-merchant payze-uz payze-pkg payze-python payze-github
Requires-Dist: requests==2.*
Requires-Dist: pydantic==2.4.2
Requires-Dist: dataclasses==0.*
